tingg_checkout/__init__.py
tingg_checkout/checkout.py
tingg_checkout/constants.py
tingg_checkout/encryption.py
tingg_checkout/validation.py
tingg_checkout-0.1.0.dist-info/METADATA
tingg_checkout-0.1.0.dist-info/WHEEL
tingg_checkout-0.1.0.dist-info/top_level.txt
tingg_checkout-0.1.0.dist-info/RECORD
