Metadata-Version: 2.1
Name: tingg-checkout
Version: 0.1.0
Summary: A package to help you streamline your integration to the Tingg Checkout API
Author: Muracia Ndungu
Author-email: platforms@cellulant.io
Classifier: Programming Language :: Python :: 3
Classifier: License :: OSI Approved :: MIT License
Classifier: Operating System :: OS Independent
Classifier: Intended Audience :: Developers
Requires-Dist: pycryptodome
